fastapi_supabase/__init__.py
fastapi_supabase/dependencies.py
fastapi_supabase/lifespan.py
fastapi_supabase/py.typed
fastapi_supabase-0.2.0.dist-info/LICENSE
fastapi_supabase-0.2.0.dist-info/METADATA
fastapi_supabase-0.2.0.dist-info/WHEEL
fastapi_supabase-0.2.0.dist-info/top_level.txt
fastapi_supabase-0.2.0.dist-info/RECORD
