Metadata-Version: 2.1
Name: fastapi-supabase
Version: 0.2.0
Summary: Integrate supabase to FastAPI with less effort
Requires-Python: >=3.9
License-File: LICENSE
Requires-Dist: fastapi>=0.115.5
Requires-Dist: supabase>=2.10.0
